baremetal_nn/__init__.py
baremetal_nn/traced_module.py
baremetal_nn-2025.4.2.dist-info/METADATA
baremetal_nn-2025.4.2.dist-info/WHEEL
baremetal_nn-2025.4.2.dist-info/top_level.txt
baremetal_nn-2025.4.2.dist-info/RECORD
