Metadata-Version: 2.4
Name: baremetal-nn
Version: 2025.4.2
Summary: Convert PyTorch models to Baremetal C/C++ code.
Home-page: https://github.com/ucb-bar/Baremetal-NN
Author: -T.K.-
Author-email: t_k_233@outlook.com
Project-URL: API Documentation, https://ucb-bar.github.io/Baremetal-NN/
Classifier: Programming Language :: Python :: 3
Classifier: License :: OSI Approved :: MIT License
Classifier: Operating System :: OS Independent
Requires-Python: >=3.8
Requires-Dist: numpy
Requires-Dist: torch
Requires-Dist: torchtune
Requires-Dist: torchao
Requires-Dist: tabulate
Dynamic: author
Dynamic: author-email
Dynamic: classifier
Dynamic: description
Dynamic: description-content-type
Dynamic: home-page
Dynamic: project-url
Dynamic: requires-dist
Dynamic: requires-python
Dynamic: summary
